YoshiOwnLib/__init__.py
YoshiOwnLib/core.py
yoshiownlib-0.1.dist-info/licenses/LICENSE
yoshiownlib-0.1.dist-info/METADATA
yoshiownlib-0.1.dist-info/WHEEL
yoshiownlib-0.1.dist-info/top_level.txt
yoshiownlib-0.1.dist-info/RECORD
